LICENSE
LICENSE.txt
MANIFEST.in
README.md
setup.cfg
setup.py
karthik_calci_00/__init__.py
karthik_calci_00/app.py
karthik_calci_00/mycalculator.py
karthik_calci_00.egg-info/PKG-INFO
karthik_calci_00.egg-info/SOURCES.txt
karthik_calci_00.egg-info/dependency_links.txt
karthik_calci_00.egg-info/entry_points.txt
karthik_calci_00.egg-info/requires.txt
karthik_calci_00.egg-info/top_level.txt
karthik_calci_00/static/index.html
karthik_calci_00/static/css/main.css
karthik_calci_00/static/css/style.css
karthik_calci_00/templates/index.html
karthik_calci_00/templates/results.html