Metadata-Version: 2.1
Name: karthik-calci-00
Version: 0.1
Summary: Simple Arithmetic Calculator
Home-page: UNKNOWN
Author: Karthik Saran
Author-email: mailmekarthik001@gmail.com
License: MIT
Keywords: calculator
Platform: UNKNOWN
Classifier: Development Status :: 3 - Alpha
Classifier: Intended Audience :: Developers
Classifier: Topic :: Software Development :: Build Tools
Classifier: License :: OSI Approved :: MIT License
Classifier: Programming Language :: Python :: 3
Classifier: Programming Language :: Python :: 3.4
Classifier: Programming Language :: Python :: 3.5
Classifier: Programming Language :: Python :: 3.6
License-File: LICENSE
License-File: LICENSE.txt
